mkdocs_madlibs/__init__.py
mkdocs_madlibs/_fence.py
mkdocs_madlibs/py.typed
mkdocs_madlibs-1.3.0.dist-info/LICENSE
mkdocs_madlibs-1.3.0.dist-info/METADATA
mkdocs_madlibs-1.3.0.dist-info/WHEEL
mkdocs_madlibs-1.3.0.dist-info/top_level.txt
mkdocs_madlibs-1.3.0.dist-info/RECORD
