Metadata-Version: 2.2
Name: mkdocs-madlibs
Version: 1.3.0
Summary: Code templating with user inputs for MkDocs superfences.
Author-email: Sam Gaudet <sam.m.gaudet@gmail.com>
Maintainer-email: Sam Gaudet <sam.m.gaudet@gmail.com>
License: MIT License
Project-URL: Homepage, http://mkdocs-madlibs.readthedocs.io/
Project-URL: Documentation, http://mkdocs-madlibs.readthedocs.io/
Project-URL: Repository, https://github.com/samgaudet/mkdocs-madlibs.git
Project-URL: Issues, https://github.com/samgaudet/mkdocs-madlibs/issues
Project-URL: Changelog, https://github.com/samgaudet/mkdocs-madlibs/blob/main/CHANGELOG.md
Keywords: mkdocs,madlibs,template,snippets
Classifier: Development Status :: 4 - Beta
Classifier: Programming Language :: Python :: 3.6
Classifier: Programming Language :: Python :: 3.7
Classifier: Programming Language :: Python :: 3.8
Classifier: Programming Language :: Python :: 3.9
Classifier: Programming Language :: Python :: 3.10
Classifier: Programming Language :: Python :: 3.11
Classifier: Programming Language :: Python :: 3.12
License-File: LICENSE
Requires-Dist: beautifulsoup4
Requires-Dist: mkdocs-material
Requires-Dist: pymdown-extensions
